sliq/__init__.py
sliq/api.py
sliq/client.py
sliq/column_validation.py
sliq/config.py
sliq/dataframe_utils.py
sliq/exceptions.py
sliq/file_utils.py
sliq/py.typed
sliq/types.py
sliq-0.1.1.dist-info/licenses/LICENSE
sliq-0.1.1.dist-info/METADATA
sliq-0.1.1.dist-info/WHEEL
sliq-0.1.1.dist-info/top_level.txt
sliq-0.1.1.dist-info/RECORD
