Metadata-Version: 2.4
Name: sliq
Version: 0.1.1
Summary: Sliq - Data cleaning, made effortless. An AI-powered data cleaning library to clean your datasets with just a few lines of code.
Author-email: Sliq Team <support@sliqdata.com>
Maintainer-email: Sliq Team <support@sliqdata.com>
License: MIT
Project-URL: Homepage, https://sliqdata.com
Project-URL: Documentation, https://sliqdata.com/docs
Keywords: data-cleaning,data-quality,machine-learning,data-analysis,data-science,ai,pandas,polars,etl,data-preprocessing,data-validation,data
Classifier: Development Status :: 4 - Beta
Classifier: Intended Audience :: Developers
Classifier: Intended Audience :: Science/Research
Classifier: Intended Audience :: Information Technology
Classifier: License :: OSI Approved :: MIT License
Classifier: Operating System :: OS Independent
Classifier: Programming Language :: Python :: 3
Classifier: Programming Language :: Python :: 3.9
Classifier: Programming Language :: Python :: 3.10
Classifier: Programming Language :: Python :: 3.11
Classifier: Programming Language :: Python :: 3.12
Classifier: Programming Language :: Python :: 3.13
Classifier: Topic :: Scientific/Engineering :: Artificial Intelligence
Classifier: Topic :: Scientific/Engineering :: Information Analysis
Classifier: Topic :: Software Development :: Libraries :: Python Modules
Classifier: Typing :: Typed
Requires-Python: >=3.9
License-File: LICENSE
Requires-Dist: requests>=2.32.5
Requires-Dist: pandas>=2.3.3
Requires-Dist: polars>=1.35.2
Requires-Dist: pyarrow>=22.0.0
Provides-Extra: dev
Requires-Dist: pytest>=7.0.0; extra == "dev"
Requires-Dist: pytest-cov>=4.0.0; extra == "dev"
Requires-Dist: mypy>=1.0.0; extra == "dev"
Requires-Dist: ruff>=0.1.0; extra == "dev"
Dynamic: license-file
